pyny3d/__init__.py
pyny3d/geoms.py
pyny3d/shadows.py
pyny3d/utils.py
pyny3d-0.2.dist-info/DESCRIPTION.rst
pyny3d-0.2.dist-info/METADATA
pyny3d-0.2.dist-info/RECORD
pyny3d-0.2.dist-info/WHEEL
pyny3d-0.2.dist-info/metadata.json
pyny3d-0.2.dist-info/top_level.txt
