Metadata-Version: 2.0
Name: pyny3d
Version: 0.2
Summary: Engineering-oriented tool to interactively build, work and perform shading simulations with 3D geometries.
Home-page: https://github.com/JoseAntFer/pyny3d
Author: José Antonio Fernández-Fernández
Author-email: joseantfer.engineer@gmail.com
License: MIT
Requires-Dist: matplotlib
Requires-Dist: numpy
Requires-Dist: scipy
Requires-Dist: shapely
